{
  "chapter_id": "03",
  "questions": [
    {
      "id": "q03-01",
      "question": "本文で説明されている、正社員の「固定給」とフリーランスの「変動報酬」の構造的な違いとして最も適切なものはどれですか。",
      "options": [
        { "id": "a", "text": "固定給は雇用契約にもとづいて毎月ほぼ一定の金額が支払われるが、変動報酬は案件数・単価・稼働時間によって月ごとに金額が変わる" },
        { "id": "b", "text": "固定給は法律で金額が決められているのに対し、変動報酬は会社が自由に金額を決めてよい" },
        { "id": "c", "text": "固定給は賞与や残業代を一切含まないが、変動報酬は賞与のみで構成される" },
        { "id": "d", "text": "固定給は年に一度まとめて支払われ、変動報酬は四半期ごとに支払われる" }
      ],
      "answer": "a",
      "explanation": "本文では、正社員の固定給は雇用契約にもとづき毎月ほぼ一定の金額が支払われ、フリーランスの変動報酬は案件数・単価・稼働時間によって月ごとに変わると説明されています。",
      "source_refs": [{ "section_id": "03-01", "anchor": "固定給と変動報酬という二つの形" }],
      "difficulty": "easy",
      "tags": ["収入", "安定性"]
    },
    {
      "id": "q03-02",
      "question": "本文では、収入の安定性を測る際に「平均年収」だけでは見誤りやすいと述べられています。その理由として最も適切なものはどれですか。",
      "options": [
        { "id": "a", "text": "同じ平均年収でも月ごとの収入のブレ幅が大きければ生活設計や資金繰りの難しさが増すため" },
        { "id": "b", "text": "平均年収は税引き前の金額しか反映されておらず、手取りの実態を表していないため" },
        { "id": "c", "text": "平均年収には賞与が含まれていないので、年収の実態より低く出るため" },
        { "id": "d", "text": "平均年収は5年単位でしか計算されず、直近の収入を反映していないため" }
      ],
      "answer": "a",
      "explanation": "本文では、年収600万円でも毎月50万円ずつ入る場合と80万円・20万円とブレる場合では生活設計のしやすさが違うと例示し、「収入のブレ幅」で見る視点を説明しています。",
      "source_refs": [{ "section_id": "03-01", "anchor": "「平均」より「ブレ幅」で見る" }],
      "difficulty": "medium",
      "tags": ["安定性", "収入のブレ幅"]
    },
    {
      "id": "q03-03",
      "question": "本文で示されている、変動報酬の「上振れと下振れは同居する」という考え方の説明として最も適切なものはどれですか。",
      "options": [
        { "id": "a", "text": "案件を増やせば収入が大きく伸びる可能性と、案件が減れば収入が大きく落ちるリスクは同じ仕組みの裏表である" },
        { "id": "b", "text": "上振れと下振れは長期的に必ず相殺されるため、年単位で見れば収入は固定給と変わらない" },
        { "id": "c", "text": "稼働を増やせば必ず単価も上がるため、下振れの可能性はほぼ存在しない" },
        { "id": "d", "text": "上振れは正社員の賞与、下振れはフリーランスの空白期間のことを指しており、両者を比較する考え方である" }
      ],
      "answer": "a",
      "explanation": "本文では、案件増や単価交渉成功による収入の伸びと、案件減による落ち込みは「同じコインの裏表」であり、自由と不安定さは表裏一体だと説明されています。",
      "source_refs": [{ "section_id": "03-01", "anchor": "上振れと下振れは同居する" }],
      "difficulty": "medium",
      "tags": ["変動報酬", "リスク"]
    },
    {
      "id": "q03-04",
      "question": "本文で説明されている、業務委託契約と正社員の雇用契約の「終了のしやすさ」の違いとして最も適切なものはどれですか。",
      "options": [
        { "id": "a", "text": "雇用契約は会社側からの一方的な終了に法律上の強い制約があるが、業務委託契約は期間満了で自然に終了するのが基本である" },
        { "id": "b", "text": "雇用契約も業務委託契約も、期間満了をもって自動的に終了する点は共通している" },
        { "id": "c", "text": "業務委託契約は法律で最低5年の継続が義務付けられており、雇用契約より終了させにくい" },
        { "id": "d", "text": "雇用契約は本人の同意がなくても会社が自由に解除できるが、業務委託契約は本人の同意が必要である" }
      ],
      "answer": "a",
      "explanation": "本文では、正社員の雇用契約は会社側からの一方的な終了に法律上の強い制約があり、業務委託契約は期間満了をもって自然に終了するのが基本だと説明されています。",
      "source_refs": [{ "section_id": "03-02", "anchor": "契約の終わり方が違う" }],
      "difficulty": "medium",
      "tags": ["契約", "業務委託契約"]
    },
    {
      "id": "q03-05",
      "question": "本文の「案件が途切れる」リスクの説明として最も適切なものはどれですか。",
      "options": [
        { "id": "a", "text": "契約が終わってから次が始まるまでの空白期間は売上がほぼゼロになる一方、生活費・社会保険料・税金などの支払いは止まらない" },
        { "id": "b", "text": "案件が途切れても、契約終了後は社会保険料や税金の支払いも自動的に止まるため、支出面の心配は少ない" },
        { "id": "c", "text": "正社員と同様、フリーランスも担当案件が終われば取引先が次の仕事を割り当ててくれるのが一般的である" },
        { "id": "d", "text": "案件の途切れはフリーランス特有の現象ではなく、正社員のプロジェクト終了と同じ意味で使われる用語である" }
      ],
      "answer": "a",
      "explanation": "本文では、案件が途切れる空白期間は売上がゼロでも生活費・社会保険料・税金の支払いは止まらず、フリーランスは自分で次を見つけるまで収入の空白が続くと説明されています。",
      "source_refs": [{ "section_id": "03-02", "anchor": "案件が「途切れる」というリスク" }],
      "difficulty": "medium",
      "tags": ["案件", "リスク"]
    },
    {
      "id": "q03-06",
      "question": "本文が示す、契約終了・案件途切れリスクへの「備え」の考え方として最も適切なものはどれですか。",
      "options": [
        { "id": "a", "text": "案件の分散・契約条件の確認・生活防衛資金などでリスクを和らげ、途切れても耐えられる状態を作っておく" },
        { "id": "b", "text": "契約条件は契約書ではなく取引先との口頭の合意のみで確認すれば十分である" },
        { "id": "c", "text": "リスクをゼロにすることが最重要で、一社専属の長期契約に絞り込むのが最良の備えである" },
        { "id": "d", "text": "生活防衛資金は案件が途切れた場合のみ役立ち、病気で働けない期間には効果がない" }
      ],
      "answer": "a",
      "explanation": "本文では、取引先の分散、契約書での更新・予告・解約条件の確認、生活防衛資金の確保を挙げ、「リスクをゼロにするのではなく、途切れても耐えられる状態を作る」発想が大切だと述べています。",
      "source_refs": [{ "section_id": "03-02", "anchor": "備えの考え方" }],
      "difficulty": "medium",
      "tags": ["備え", "案件の分散"]
    },
    {
      "id": "q03-07",
      "question": "本文で説明されている、病気・休業・退職時の保障に関する正社員とフリーランスの違いとして最も適切なものはどれですか。",
      "options": [
        { "id": "a", "text": "正社員は傷病手当金・有給休暇・退職金など保障が雇用に組み込まれているのに対し、フリーランスはこれらが原則なく、保障を自分で組み立てる必要がある" },
        { "id": "b", "text": "フリーランスも国民健康保険から正社員と同等の傷病手当金を受けられるため、休業時の収入面では大きな差はない" },
        { "id": "c", "text": "有給休暇や退職金はフリーランスにも法律で同様に付与されるが、申請手続きが煩雑な点だけが異なる" },
        { "id": "d", "text": "正社員には所得補償保険が法律で義務付けられており、フリーランスはこの保険に加入できない" }
      ],
      "answer": "a",
      "explanation": "本文では、正社員には傷病手当金・有給休暇・退職金などが用意されている一方、フリーランスは国民健康保険に傷病手当金にあたる制度が基本的になく、有給休暇や退職金もないため、貯蓄や民間保険などで自分で備える必要があると説明されています。",
      "source_refs": [
        { "section_id": "03-03", "anchor": "保障の有無を対比で見る" },
        { "section_id": "03-03", "anchor": "フリーランスは自分で備える" }
      ],
      "difficulty": "medium",
      "tags": ["保障", "傷病手当金", "社会保険"]
    }
  ]
}
