{
  "chapter_id": "05",
  "questions": [
    {
      "id": "q05-01",
      "question": "起業の最初の一歩として、本文が最も大切だとしている考え方はどれですか。",
      "options": [
        { "id": "a", "text": "アイデアが誰かに求められているかを、現実の反応で確かめること" },
        { "id": "b", "text": "立派なサービスをまず完成させ、品質に自信を持ってから世に出すこと" },
        { "id": "c", "text": "事業計画書を綿密に作り込み、関係者からの合意を取り付けること" },
        { "id": "d", "text": "競合他社の動きを詳細に分析し、勝てる領域を見定めること" }
      ],
      "answer": "a",
      "explanation": "本文では、最初の一歩で大切なのは作り込むことではなく、アイデアが求められているかを現実の反応で確かめることだと述べられています。bは「作り込んでから出す」考え方で、本文が戒めている進め方です。",
      "source_refs": [
        { "section_id": "05-01", "anchor": "最初の一歩は「作る」より「確かめる」" }
      ],
      "difficulty": "easy",
      "tags": ["アイデア検証", "起業の準備"]
    },
    {
      "id": "q05-02",
      "question": "本文で説明されている「スモールスタート」の進め方として最も適切なものはどれですか。",
      "options": [
        { "id": "a", "text": "最初から大きな設備に投資し、量産体制を整えてから販売を始める" },
        { "id": "b", "text": "アンケートで好意的な回答を多く集めてから、本格的に開発を始める" },
        { "id": "c", "text": "小さく・安く始めて、顧客の実際の反応を見ながら少しずつ育てる" },
        { "id": "d", "text": "完成度の高い試作品を一気に作り上げ、大規模に告知して反応を見る" }
      ],
      "answer": "c",
      "explanation": "スモールスタートは、最初から完璧を目指さず小さく・安く始めて、顧客の反応を見ながら育てていく進め方です。bはアンケートの好意的回答に頼る点が本文の趣旨と異なります(本文では対価を払う相手がいるかを確かめる重要性が強調されています)。",
      "source_refs": [
        { "section_id": "05-01", "anchor": "スモールスタート — 小さく試して育てる" }
      ],
      "difficulty": "easy",
      "tags": ["スモールスタート", "アイデア検証"]
    },
    {
      "id": "q05-03",
      "question": "本文で挙げられている、起業初期によくある失敗のパターンに含まれないものはどれですか。",
      "options": [
        { "id": "a", "text": "需要を確かめずに製品やサービスを作り込んでしまう" },
        { "id": "b", "text": "需要が読めない段階で固定費を早く増やしすぎる" },
        { "id": "c", "text": "資金繰りの見通しが甘く、現金が足りなくなる" },
        { "id": "d", "text": "海外の最新トレンドを取り入れず、国内市場に閉じこもる" }
      ],
      "answer": "d",
      "explanation": "本文で挙げられている典型的な失敗は「需要を確かめずに作り込む」「資金繰りの見通しが甘い」「固定費を早く増やしすぎる」「ひとりで抱え込み相談しない」の4つです。dは本文では扱われていません。",
      "source_refs": [
        { "section_id": "05-02", "anchor": "失敗には繰り返されるパターンがある" }
      ],
      "difficulty": "easy",
      "tags": ["よくある失敗", "起業のリスク"]
    },
    {
      "id": "q05-04",
      "question": "本文で説明されている「黒字倒産」の意味として最も適切なものはどれですか。",
      "options": [
        { "id": "a", "text": "売上が大きく赤字が続いた結果、銀行から融資を打ち切られて事業が止まる状態" },
        { "id": "b", "text": "帳簿上は利益が出ているのに、手元の現金が足りず支払いができなくなる状態" },
        { "id": "c", "text": "黒字が続いたことで税負担が重くなりすぎ、納税のために廃業を選ぶ状態" },
        { "id": "d", "text": "売上はあるが原価が高く、利益率がほぼゼロのまま事業を続けてしまう状態" }
      ],
      "answer": "b",
      "explanation": "本文では、帳簿上は黒字でも入金より先に支払いが来て現金が尽き、行き詰まる状態を「黒字倒産」と説明しています。aは赤字が前提なので「黒字倒産」とは言いません。利益と現金は別物だという点がポイントです。",
      "source_refs": [
        { "section_id": "05-02", "anchor": "お金が回らなくなる — 資金繰りの失敗" }
      ],
      "difficulty": "easy",
      "tags": ["資金繰り", "黒字倒産"]
    },
    {
      "id": "q05-05",
      "question": "副業から始めて段階的に独立する進め方について、本文の説明として最も適切なものはどれですか。",
      "options": [
        { "id": "a", "text": "本業の収入を保ったまま事業を試せるので、追い詰められず冷静に検証しやすい" },
        { "id": "b", "text": "副業の段階で一件でも大きな受注が取れたら、すぐに本業を辞めて独立すべきである" },
        { "id": "c", "text": "退路を断つほうが本気度が増すため、副業を経ずに会社を辞めてから始めるのが望ましい" },
        { "id": "d", "text": "副業中は税務や就業規則を気にせず、独立後にまとめて手続きすればよい" }
      ],
      "answer": "a",
      "explanation": "本文では、副業は本業の収入を保ったまま検証ができ、資金繰りに追い詰められず冷静に判断しやすい点が利点として説明されています。bは「たまたまの一件で勢いづいた段階で辞める」失敗パターンに近く、本文の趣旨と異なります。",
      "source_refs": [
        { "section_id": "05-03", "anchor": "いきなり辞めない — 副業という入り口" },
        { "section_id": "05-03", "anchor": "段階的に独立する" }
      ],
      "difficulty": "easy",
      "tags": ["副業", "段階的な独立", "リスク管理"]
    },
    {
      "id": "q05-06",
      "question": "本文で説明されている「生活防衛資金」として最も適切な説明はどれですか。",
      "options": [
        { "id": "a", "text": "事業に必要な仕入れや家賃を毎月支払うために確保しておく、事業用の運転資金のこと" },
        { "id": "b", "text": "将来の大きな投資に備え、事業の利益から積み立てておく内部留保のこと" },
        { "id": "c", "text": "起業時に金融機関から借りる、開業のための借入金のこと" },
        { "id": "d", "text": "収入が一時的に途絶えても暮らしを維持できるよう、生活費の数か月分を手元に確保しておくお金のこと" }
      ],
      "answer": "d",
      "explanation": "本文では生活防衛資金を「収入が一時的に途絶えても暮らしを維持できるよう、生活費の数か月分を手元に確保しておくお金」と定義しています。aの運転資金は事業を回すためのお金で、生活防衛資金とは別物です。",
      "source_refs": [
        { "section_id": "05-03", "anchor": "始める前に確認・準備しておくこと" }
      ],
      "difficulty": "easy",
      "tags": ["生活防衛資金", "リスク管理"]
    }
  ]
}
